biauek/__init__.py
biauek/cli.py
biauek/lib.py
biauek-0.4.1.dist-info/LICENSE.md
biauek-0.4.1.dist-info/METADATA
biauek-0.4.1.dist-info/WHEEL
biauek-0.4.1.dist-info/entry_points.txt
biauek-0.4.1.dist-info/top_level.txt
biauek-0.4.1.dist-info/RECORD
