Metadata-Version: 2.1
Name: biauek
Version: 0.4.1
Summary: if you know, you know
Home-page: https://codeberg.org/coralpink/biauek
Author: Coral Pink
Author-email: coral.pink@disr.it
Requires-Python: >=3.7
License-File: LICENSE.md
Requires-Dist: aiohttp (<4.0,>=3.8)
